quiet_riot/__init__.py
quiet_riot/main.py
quiet_riot/settings.py
quiet_riot/total_footprint_wordlist.py
quiet_riot/enumeration/codeartifactenum.py
quiet_riot/enumeration/ecrprivenum.py
quiet_riot/enumeration/ecrpubenum.py
quiet_riot/enumeration/iamassumeroleenum.py
quiet_riot/enumeration/lambdaenum.py
quiet_riot/enumeration/loadbalancer.py
quiet_riot/enumeration/rand_id_generator.py
quiet_riot/enumeration/s3aclenum.py
quiet_riot/enumeration/s3enum.py
quiet_riot/enumeration/secretsmanagerenum.py
quiet_riot/enumeration/snsenum.py
quiet_riot/results/scan-run-statistics.txt
quiet_riot/results/valid_scan_results.txt
quiet_riot/wordlists/familynames-usa-top1000.txt
quiet_riot/wordlists/femalenames-usa-top1000.txt
quiet_riot/wordlists/github-scrape.txt
quiet_riot/wordlists/known_valid_account_ids.txt
quiet_riot/wordlists/malenames-usa-top1000.txt
quiet_riot/wordlists/service-linked-roles.txt
quiet_riot-1.0.6.dist-info/METADATA
quiet_riot-1.0.6.dist-info/WHEEL
quiet_riot-1.0.6.dist-info/entry_points.txt
quiet_riot-1.0.6.dist-info/top_level.txt
quiet_riot-1.0.6.dist-info/RECORD
