Metadata-Version: 2.1
Name: quiet_riot
Version: 1.0.6
Summary: Cloud Recon Tool
Home-page: https://github.com/pypa/sampleproject
Author: Wess ladd
Author-email: wesladd@traingrc.com
Classifier: Programming Language :: Python :: 3
Classifier: Operating System :: OS Independent
Requires-Python: >=3.7
